dupeutil/__init__.py
dupeutil/__version__.py
dupeutil/console.py
dupeutil/core.py
dupeutil/main.py
dupeutil/utils.py
dupeutil-1.0.0.dist-info/LICENSE
dupeutil-1.0.0.dist-info/METADATA
dupeutil-1.0.0.dist-info/WHEEL
dupeutil-1.0.0.dist-info/entry_points.txt
dupeutil-1.0.0.dist-info/top_level.txt
dupeutil-1.0.0.dist-info/RECORD
