Metadata-Version: 2.1
Name: dupeutil
Version: 1.0.0
Summary: A command-line program written in Python for detecting and removing duplicate files
Home-page: https://github.com/giosali/dupeutil
Author: Giovanni Salinas
Author-email: gio_sali@outlook.com
License: MIT
Project-URL: Source, https://github.com/giosali/dupeutil
Keywords: duplicate,files,commandline,dupeutil
Platform: UNKNOWN
Classifier: Development Status :: 5 - Production/Stable
Classifier: Intended Audience :: End Users/Desktop
Classifier: License :: OSI Approved :: MIT License
Classifier: Natural Language :: English
Classifier: Operating System :: OS Independent
Classifier: Programming Language :: Python :: 3.6
Classifier: Programming Language :: Python :: 3.7
Classifier: Programming Language :: Python :: 3.8
Classifier: Programming Language :: Python :: 3.9
Classifier: Programming Language :: Python :: 3.10
Classifier: Topic :: Software Development :: Libraries
Requires-Python: >=3.6, <4
License-File: LICENSE
